dttlib/__init__.py
dttlib/__init__.pyi
dttlib/dttlib.cpython-311-x86_64-linux-gnu.so
dttlib/py.typed
dttlib-0.10.4.dist-info/METADATA
dttlib-0.10.4.dist-info/WHEEL
dttlib-0.10.4.dist-info/licenses/COPYING
dttlib-0.10.4.dist-info/licenses/COPYING-GPL-3
dttlib.libs/libfftw3-7229d6f2.so.3
dttlib.libs/libfftw3f-3af7c840.so.3
dttlib.libs/libgds-sigp-94f0a788.so
dttlib.libs/libndsclient-5ff49674.so.1
dttlib.libs/libndscxx-78126e77.so.1
dttlib.libs/libsasl2-86ae7ca3.so.2
dttlib-0.10.4.dist-info/RECORD
