Metadata-Version: 2.4
Name: dttlib
Version: 0.10.4
License-File: COPYING
License-File: COPYING-GPL-3
Summary: Advanced LIGO core library for online and offline frequency-domain diagnostics tool.
Keywords: dtt,diaggui,fft,swept-sine
Home-Page: https://git.ligo.org/cds/software/cr-tools/dtt_rust
Author: Erik von Reis <erik.vonreis@ligo.org>
Author-email: Erik von Reis <erik.vonreis@ligo.org>
Requires-Python: >=3.9
